pencroft/__init__.py
pencroft/__main__.py
pencroft/benchmark.py
pencroft/cli.py
pencroft/monkey.py
pencroft/loaders/__init__.py
pencroft/loaders/folder.py
pencroft/loaders/loader.py
pencroft/loaders/tarfile.py
pencroft/loaders/zipfile.py
pencroft-0.5.dist-info/DESCRIPTION.rst
pencroft-0.5.dist-info/METADATA
pencroft-0.5.dist-info/RECORD
pencroft-0.5.dist-info/WHEEL
pencroft-0.5.dist-info/metadata.json
pencroft-0.5.dist-info/top_level.txt
tests/__init__.py
tests/conftest.py
tests/test_benchmark.py
tests/test_loader.py
