Metadata-Version: 2.0
Name: pencroft
Version: 0.5
Summary: UNKNOWN
Home-page: UNKNOWN
Author: UNKNOWN
Author-email: UNKNOWN
License: BSD
Platform: UNKNOWN
Provides-Extra: test
Requires-Dist: flake8; extra == 'test'
Requires-Dist: pytest; extra == 'test'
